s3_helper/__init__.py
s3_helper/cli/__init__.py
s3_helper/cli/aws.py
s3_helper/cli/s3.py
s3_helper/process/__init__.py
s3_helper/process/aws_process.py
s3_helper/process/download.py
s3_helper/process/initializer.py
s3_helper/process/s3_process.py
s3_helper/process/upload.py
s3_helper/utils/__init__.py
s3_helper/utils/progress.py
s3_helper/utils/tree.py
s3_helper/utils/util.py
s3_helper-0.0.2.dist-info/entry_points.txt
s3_helper-0.0.2.dist-info/LICENSE
s3_helper-0.0.2.dist-info/METADATA
s3_helper-0.0.2.dist-info/WHEEL
s3_helper-0.0.2.dist-info/RECORD
