Metadata-Version: 2.1
Name: s3-helper
Version: 0.0.2
Summary: A Developer friendly S3 manager to upload and download files.
License: AGPL-3.0-or-later
Author: Code63Reaper
Author-email: akilangms542@gmail.com
Maintainer: Code63Reaper
Maintainer-email: akilangms542@gmail.com
Requires-Python: >=3.10,<4.0
Classifier: Development Status :: 2 - Pre-Alpha
Classifier: Intended Audience :: Developers
Classifier: License :: OSI Approved :: GNU Affero General Public License v3 or later (AGPLv3+)
Classifier: Programming Language :: Python :: 3
Classifier: Programming Language :: Python :: 3.10
Classifier: Programming Language :: Python :: 3.11
Classifier: Programming Language :: Python :: 3.12
Classifier: Programming Language :: Python :: 3 :: Only
Classifier: Topic :: Utilities
Requires-Dist: boto3 (>=1.34.117,<2.0.0)
Requires-Dist: rich (>=13.7.1,<14.0.0)
Requires-Dist: toml (>=0.10.2,<0.11.0)
